teamscalerobotplugin/AgentConnector.py
teamscalerobotplugin/RobotTestFinder.py
teamscalerobotplugin/TiaRobotListener.py
teamscalerobotplugin/UniformPathUtil.py
teamscalerobotplugin/__init__.py
teamscalerobotplugin-0.0.4b0.dist-info/LICENSE
teamscalerobotplugin-0.0.4b0.dist-info/METADATA
teamscalerobotplugin-0.0.4b0.dist-info/WHEEL
teamscalerobotplugin-0.0.4b0.dist-info/top_level.txt
teamscalerobotplugin-0.0.4b0.dist-info/RECORD
